wev_awsmfa/VERSION
wev_awsmfa/__init__.py
wev_awsmfa/aws.py
wev_awsmfa/conftest.py
wev_awsmfa/plugin.py
wev_awsmfa/test_aws.py
wev_awsmfa/test_plugin.py
wev_awsmfa/test_version.py
wev_awsmfa/version.py
wev_awsmfa-1.1.0.dist-info/LICENSE
wev_awsmfa-1.1.0.dist-info/METADATA
wev_awsmfa-1.1.0.dist-info/WHEEL
wev_awsmfa-1.1.0.dist-info/entry_points.txt
wev_awsmfa-1.1.0.dist-info/top_level.txt
wev_awsmfa-1.1.0.dist-info/RECORD
